dash_credit_cards/DashCreditCardInput.py
dash_credit_cards/DashCreditCards.py
dash_credit_cards/DashParallaxTilt.py
dash_credit_cards/__init__.py
dash_credit_cards/_imports_.py
dash_credit_cards/dash_credit_cards.min.js
dash_credit_cards/dash_credit_cards.min.js.map
dash_credit_cards/metadata.json
dash_credit_cards/package-info.json
dash_credit_cards-0.0.1.dist-info/LICENSE
dash_credit_cards-0.0.1.dist-info/METADATA
dash_credit_cards-0.0.1.dist-info/WHEEL
dash_credit_cards-0.0.1.dist-info/top_level.txt
dash_credit_cards-0.0.1.dist-info/RECORD
