Metadata-Version: 2.1
Name: dash-credit-cards
Version: 0.0.1
Summary: credit card templates and form for dash
Author: pip install python <pipinstallpython@gmail.com>
License: MIT
Classifier: Framework :: Dash
License-File: LICENSE
